rbible/__init__.py
rbible/bible_data.py
rbible/bible_reader.py
rbible/formatters.py
rbible/rbible.py
rbible/reference_detector.py
rbible/user_data.py
rbible/verse_operations.py
rbible-1.0.5.dist-info/licenses/LICENSE
rbible-1.0.5.dist-info/METADATA
rbible-1.0.5.dist-info/WHEEL
rbible-1.0.5.dist-info/entry_points.txt
rbible-1.0.5.dist-info/top_level.txt
rbible-1.0.5.dist-info/RECORD
