Metadata-Version: 2.4
Name: rbible
Version: 1.0.5
Summary: A command-line Bible verse lookup tool
Author-email: Roberto Ram <your.email@example.com>
License: MIT
Project-URL: Homepage, https://github.com/robertoram/rbible
Project-URL: Bug Tracker, https://github.com/robertoram/rbible/issues
Keywords: bible,verse,lookup,cli
Classifier: Programming Language :: Python :: 3
Classifier: License :: OSI Approved :: MIT License
Classifier: Operating System :: OS Independent
Classifier: Development Status :: 4 - Beta
Classifier: Environment :: Console
Classifier: Topic :: Religion
Classifier: Topic :: Utilities
Requires-Python: >=3.6
License-File: LICENSE
Requires-Dist: argparse
Requires-Dist: pyperclip
Dynamic: license-file
